{"slot-registration":{"break_key":"break-registration"},"slot-hello-world":{"break_key":"break-hello-world"},"slot-1":{"venue-tomtom":{"talk_key":"talk-how-to-combine-swift"},"venue-htd":{"talk_key":"talk-tbd"},"venue-rndity":{"talk_key":"talk-tbd"},"venue-mobica":{"talk_key":"talk-augmented-reality"},"venue-seqr":{"talk_key":"talk-devops-in-mobile"}},"slot-coffee-1":{"break_key":"break-coffee"},"slot-2":{"venue-tomtom":{"talk_key":"talk-tbd"},"venue-htd":{"talk_key":"talk-tbd"},"venue-rndity":{"talk_key":"talk-tbd"},"venue-mobica":{"talk_key":"talk-tbd"},"venue-seqr":{"talk_key":"talk-tbd"}},"slot-coffee-2":{"break_key":"break-coffee"},"slot-3":{"venue-tomtom":{"talk_key":"talk-tbd"},"venue-htd":{"talk_key":"talk-tbd"},"venue-rndity":{"talk_key":"talk-tbd"},"venue-mobica":{"talk_key":"talk-tbd"},"venue-seqr":{"talk_key":"talk-tbd"}},"slot-lunch":{"break_key":"break-lunch"},"slot-4":{"venue-tomtom":{"talk_key":"talk-tbd"},"venue-htd":{"talk_key":"talk-tbd"},"venue-rndity":{"talk_key":"talk-tbd"},"venue-mobica":{"talk_key":"talk-tbd"},"venue-seqr":{"talk_key":"talk-tbd"}},"slot-coffee-4":{"break_key":"break-coffee"},"slot-5":{"venue-tomtom":{"talk_key":"talk-tbd"},"venue-htd":{"talk_key":"talk-tbd"},"venue-rndity":{"talk_key":"talk-tbd"},"venue-mobica":{"talk_key":"talk-tbd"},"venue-seqr":{"talk_key":"talk-tbd"}},"slot-coffee-5":{"break_key":"break-coffee"},"slot-6":{"venue-tomtom":{"talk_key":"talk-tbd"},"venue-htd":{"talk_key":"talk-tbd"},"venue-rndity":{"talk_key":"talk-tbd"},"venue-mobica":{"talk_key":"talk-tbd"},"venue-seqr":{"talk_key":"talk-tbd"}},"slot-coffee-6":{"break_key":"break-coffee"},"slot-7":{"venue-tomtom":{"talk_key":"talk-tbd"},"venue-htd":{"talk_key":"talk-tbd"},"venue-rndity":{"talk_key":"talk-tbd"},"venue-mobica":{"talk_key":"talk-tbd"},"venue-seqr":{"talk_key":"talk-tbd"}},"slot-coffee-7":{"break_key":"break-coffee"},"slot-8":{"venue-tomtom":{"talk_key":"talk-tbd"},"venue-htd":{"talk_key":"talk-tbd"},"venue-rndity":{"talk_key":"talk-tbd"},"venue-mobica":{"talk_key":"talk-tbd"},"venue-seqr":{"talk_key":"talk-tbd"}},"slot-no-coffee-8":{"break_key":"break-no-coffee"},"slot-finally":{"break_key":"break-finally"},"slot-afterparty":{"break_key":"break-afterparty"}}